{
    "category": "@@TODO: Geometry",
    "description": "@@TODO: This sample demonstrates how to cut a geometry with a polyline using the GeometryEngine",
    "ignore": false,
    "images": [
        "screenshot.png"
    ],
    "keywords": [
        "geometry",
        " cut",
        " split"
    ],
    "redirect_from": "@@TODO: /qt/latest/qml/sample-qt-cutgeometry.htm",
    "relevant_apis": [
        "GeometryEngine",
        "GeometryEngine::cut"
    ],
    "snippets": [
        "@@TODO: *** PLEASE VERIFY THE INCLUSION OF THESE SNIPPETS ***",
        "CutGeometry.qml"
    ],
    "title": "@@TODO: Cut geometry"
}