{
    "category": "Cloud and portal",
    "description": "Connect to Portal to give users access to their organization's basemaps.",
    "ignore": false,
    "images": [
        "screenshot.png"
    ],
    "keywords": [
        "basemap",
        "integration",
        "organization",
        "portal",
        "Portal",
        "Portal::fetchBasemaps"
    ],
    "redirect_from": [
        "/qt/latest/cpp/sample-code/sample-qt-showorgbasemaps.htm"
    ],
    "relevant_apis": [
        "Portal",
        "Portal::fetchBasemaps"
    ],
    "snippets": [
        "ShowOrgBasemaps.qml",
        "ShowOrgBasemaps.cpp",
        "ShowOrgBasemaps.h"
    ],
    "title": "Show organization basemaps"
}
