{
    "category": "Scenes",
    "description": "Position graphics relative to a surface using different surface placement modes.",
    "featured": false,
    "ignore": false,
    "images": [
        "screenshot.png"
    ],
    "keywords": [
        "3D",
        "absolute",
        "altitude",
        "draped",
        "elevation",
        "floating",
        "relative",
        "scenes",
        "sea level",
        "surface placement",
        "Graphic",
        "GraphicsOverlay",
        "LayerSceneProperties.surfacePlacement",
        "SceneProperties",
        "Surface"
    ],
    "redirect_from": [
        "/qt/latest/qml/sample-code/sample-qt-surfaceplacement.htm",
        "/qt/latest/qml/sample-code/sample-qt-surface-placement.htm"
    ],
    "relevant_apis": [
        "Graphic",
        "GraphicsOverlay",
        "LayerSceneProperties.surfacePlacement",
        "SceneProperties",
        "Surface"
    ],
    "snippets": [
        "SetSurfacePlacementMode.qml"
    ],
    "title": "Set surface placement mode"
}
