{
    "category": "@@TODO: Features",
    "description": "@@TODO: This sample demonstrates how to query a layer for features that are in a related table",
    "ignore": false,
    "images": [
        "screenshot.png"
    ],
    "keywords": [
        "@@TODO: *** PLEASE ADD ADDITIONAL KEYWORDS ***",
        "ArcGISFeatureTable",
        "ArcGISFeature",
        "RelatedFeatureQueryResult",
        "FeatureQueryResult",
        "FeatureIterator",
        "Map",
        "MapView",
        "FeatureLayer"
    ],
    "redirect_from": "@@TODO: /qt/latest/qml/sample-qt-listrelatedfeatures.htm",
    "relevant_apis": [
        "ArcGISFeatureTable",
        "ArcGISFeature",
        "RelatedFeatureQueryResult",
        "FeatureQueryResult",
        "FeatureIterator",
        "Map",
        "MapView",
        "FeatureLayer"
    ],
    "snippets": [
        "@@TODO: *** PLEASE VERIFY THE INCLUSION OF THESE SNIPPETS ***",
        "ListRelatedFeatures.qml"
    ],
    "title": "@@TODO: List related features"
}