{
    "category": "Local Server",
    "dataItems": [
        {
            "itemId": "ab8647d60dfd413babffa815bbb12095",
            "path": "~/ArcGIS/Runtime/Data/mpk/PointsofInterest.mpkx"
        },
        {
            "itemId": "7c4994a31470460798afb07a282b438a",
            "path": "~/ArcGIS/Runtime/Data/gpkx/Contour.gpkx"
        }
    ],
    "description": "Demonstrates how to start and stop the Local Server and start and stop a local map, feature, and geoprocessing service running on the Local Server.",
    "ignore": false,
    "images": [
        "screenshot.png"
    ],
    "keywords": [
        "feature",
        "geoprocessing",
        "local services",
        "map",
        "server",
        "service",
        "LocalFeatureService",
        "LocalGeoprocessingService",
        "LocalMapService",
        "LocalServer",
        "LocalServerStatus",
        "LocalService"
    ],
    "redirect_from": [
        "/qt/latest/cpp/sample-code/sample-qt-localserverservices.htm"
    ],
    "relevant_apis": [
        "LocalFeatureService",
        "LocalGeoprocessingService",
        "LocalMapService",
        "LocalServer",
        "LocalServerStatus",
        "LocalService"
    ],
    "snippets": [
        "LocalServerServices.qml",
        "LocalServerServices.cpp",
        "LocalServerServices.h"
    ],
    "title": "Local server services"
}
