{
    "category": "@@TODO: Analysis",
    "description": "@@TODO: Show a line of sight between two moving objects",
    "ignore": false,
    "images": [
        "screenshot.png"
    ],
    "keywords": [
        "Analysis",
        " line of sight",
        " visibility",
        "AnalysisOverlay",
        "GeoElementLineOfSight",
        "LineOfSight::targetVisibility"
    ],
    "redirect_from": "@@TODO: /qt/latest/cpp/sample-code/sample-qt-lineofsightgeoelement.htm",
    "relevant_apis": [
        "AnalysisOverlay",
        "GeoElementLineOfSight",
        "LineOfSight::targetVisibility"
    ],
    "snippets": [
        "@@TODO: *** PLEASE VERIFY THE INCLUSION OF THESE SNIPPETS ***",
        "LineOfSightGeoElement.cpp",
        "LineOfSightGeoElement.h",
        "main.qml",
        "LineOfSightGeoElement.qml"
    ],
    "title": "@@TODO: Line of sight (geoelement)"
}